backend/__init__.py
backend/vcs/__init__.py
backend/vcs/branch.py
backend/vcs/commit.py
backend/vcs/core.py
backend/vcs/diff.py
backend/vcs/diff_calculator.py
backend/vcs/graph.py
backend/vcs/hooks.py
backend/vcs/ignore.py
backend/vcs/merge.py
backend/vcs/remote.py
backend/vcs/stash.py
backend/vcs/submodule.py
backend/vcs/tag.py
backend/vcs/tree.py
cli/__init__.py
cli/hrs_cli.py
cli/vcs_cli.py
hermes_revision_system-0.1.0.dist-info/LICENSE
hermes_revision_system-0.1.0.dist-info/METADATA
hermes_revision_system-0.1.0.dist-info/WHEEL
hermes_revision_system-0.1.0.dist-info/entry_points.txt
hermes_revision_system-0.1.0.dist-info/top_level.txt
hermes_revision_system-0.1.0.dist-info/RECORD
