Metadata-Version: 2.2
Name: hermes-revision-system
Version: 0.1.0
Summary: Hermes Revision System - современная система контроля версий
Home-page: https://github.com/SomeMedic/hermes-revision-system
Author: SomeMedic
Author-email: maxg2015maxg@gmail.com
Project-URL: Bug Tracker, https://github.com/SomeMedic/hermes-revision-system/issues
Project-URL: Documentation, https://github.com/SomeMedic/hermes-revision-system/wiki
Project-URL: Source Code, https://github.com/SomeMedic/hermes-revision-system
Keywords: hrs,hermes,version control,git,vcs,система контроля версий
Classifier: Development Status :: 3 - Alpha
Classifier: Intended Audience :: Developers
Classifier: Topic :: Software Development :: Version Control
Classifier: Topic :: Software Development :: Version Control :: Git
Classifier: Programming Language :: Python :: 3
Classifier: Programming Language :: Python :: 3.8
Classifier: Programming Language :: Python :: 3.9
Classifier: Programming Language :: Python :: 3.10
Classifier: Programming Language :: Python :: 3.11
Classifier: License :: OSI Approved :: MIT License
Classifier: Operating System :: OS Independent
Classifier: Natural Language :: Russian
Classifier: Natural Language :: English
Requires-Python: >=3.8
License-File: LICENSE
Requires-Dist: click>=8.1.7
Requires-Dist: watchdog>=3.0.0
Requires-Dist: python-dotenv>=1.0.0
Requires-Dist: graphviz>=0.20.1
Provides-Extra: dev
Requires-Dist: pytest>=7.4.0; extra == "dev"
Requires-Dist: black>=23.12.1; extra == "dev"
Requires-Dist: flake8>=7.0.0; extra == "dev"
Dynamic: author
Dynamic: author-email
Dynamic: classifier
Dynamic: description
Dynamic: description-content-type
Dynamic: home-page
Dynamic: keywords
Dynamic: project-url
Dynamic: provides-extra
Dynamic: requires-dist
Dynamic: requires-python
Dynamic: summary
